Metadata-Version: 2.1
Name: clinalyse
Version: 1.0.0
Summary: Module for analysing multi-locus clines
Download-URL: https://github.com/Studenecivb/clinalyse/archive/refs/tags/v1.0.0.tar.gz
Author: Nina Haladova & Stuart JE Baird
Author-email: ninahaladova@gmail.com
